Metadata-Version: 1.1
Name: elastic-git
Version: 1.4.2
Summary: JSON Object storage backed by Git & Elastic Search
Home-page: http://github.com/universalcore/elastic-git
Author: Praekelt Foundation
Author-email: unicore-team@praekeltconsulting.com
License: BSD
Keywords: git elasticsearch json
Platform: UNKNOWN
Classifier: Programming Language :: Python
